Metadata-Version: 1.0
Name: afaans-distribution
Version: 0.1
Summary: Gaussian and Binomial distributions
Home-page: UNKNOWN
Author: Affan Shariff
Author-email: afaanshariff29@gmail.com
License: UNKNOWN
Platform: UNKNOWN
